iflow_mcp_talhaorak_mcp_taiga_bridge-0.1.1.dist-info/licenses/LICENSE
src/__init__.py
src/config.py
src/server.py
src/taiga_client.py
iflow_mcp_talhaorak_mcp_taiga_bridge-0.1.1.dist-info/METADATA
iflow_mcp_talhaorak_mcp_taiga_bridge-0.1.1.dist-info/WHEEL
iflow_mcp_talhaorak_mcp_taiga_bridge-0.1.1.dist-info/top_level.txt
iflow_mcp_talhaorak_mcp_taiga_bridge-0.1.1.dist-info/RECORD
