Metadata-Version: 2.4
Name: iflow-mcp_talhaorak_mcp-taiga-bridge
Version: 0.1.1
Summary: Taiga integration bridge for MCP
Author-email: Talha Orak <talhaorak.git@gmail.com>
Requires-Python: >=3.10
License-File: LICENSE
Requires-Dist: mcp[cli]>=0.1.0
Requires-Dist: python-dotenv>=0.15.0
Requires-Dist: pydantic>=2.4.0
Requires-Dist: pydantic-settings>=2.0.0
Requires-Dist: pytaigaclient>=0.1.0
Provides-Extra: dev
Requires-Dist: pytest>=8.3.5; extra == "dev"
Requires-Dist: pytest-asyncio>=0.21.0; extra == "dev"
Requires-Dist: pytest-cov>=4.1.0; extra == "dev"
Requires-Dist: ruff>=0.8.0; extra == "dev"
Requires-Dist: mypy>=1.3.0; extra == "dev"
Dynamic: license-file
